plover_retro_stringop/__init__.py
plover_retro_stringop-0.1.2.dist-info/METADATA
plover_retro_stringop-0.1.2.dist-info/WHEEL
plover_retro_stringop-0.1.2.dist-info/entry_points.txt
plover_retro_stringop-0.1.2.dist-info/top_level.txt
plover_retro_stringop-0.1.2.dist-info/zip-safe
plover_retro_stringop-0.1.2.dist-info/RECORD
