Metadata-Version: 2.1
Name: plover-retro-stringop
Version: 0.1.2
Summary: Run arbitrary Python code on the last n words!
Home-page: https://github.com/buffet/plover_retro_stringop
Author: Niclas Meyer
Author-email: niclas@countingsort.com
License: MIT
Keywords: plover plover_plugin
Platform: UNKNOWN
Requires-Dist: plover (>=4.0.0.dev7)
